pydejavu/__init__.py
pydejavu/__main__.py
pydejavu/compilation/__init__.py
pydejavu/compilation/scala_monitor_compiler.py
pydejavu/compilation/spec_parser_synthesizer.py
pydejavu/core/__init__.py
pydejavu/core/event_operational_mapper.py
pydejavu/core/monitor.py
pydejavu/core/shared_state.py
pydejavu/core/verify.py
pydejavu/jni/__init__.py
pydejavu/jni/jni_config.py
pydejavu/jni/linkage_monitor.py
pydejavu/libs/dejavu.jar
pydejavu/libs/scala-library.jar
pydejavu/utils/__init__.py
pydejavu/utils/benchmark_util.py
pydejavu/utils/file_utils.py
pydejavu/utils/logger.py
pydejavu/utils/monitor_generator.py
pydejavu_rv-1.0.0.dist-info/LICENSE
pydejavu_rv-1.0.0.dist-info/METADATA
pydejavu_rv-1.0.0.dist-info/WHEEL
pydejavu_rv-1.0.0.dist-info/entry_points.txt
pydejavu_rv-1.0.0.dist-info/RECORD
