Metadata-Version: 2.1
Name: PyDejaVu-RV
Version: 1.0.0
Summary: PyDejaVu is a Python implementation that wraps the original DejaVu jar file, providing a bridge between Python and the Java-based DejaVu runtime verification tool. This wrapper extends DejaVu's functionality by supporting a 2-phase monitoring approach.
Home-page: https://github.com/moraneus/pydejavu
License: Apache-2.0
Keywords: runtime verification,dejavu,monitoring,java bridge
Author: moraneus
Author-email: moraneus@gmail.com
Requires-Python: >=3.8,<4.0
Classifier: Development Status :: 4 - Beta
Classifier: Intended Audience :: Developers
Classifier: License :: OSI Approved :: Apache Software License
Classifier: Programming Language :: Python :: 3
Classifier: Programming Language :: Python :: 3.8
Classifier: Programming Language :: Python :: 3.9
Classifier: Programming Language :: Python :: 3.10
Classifier: Programming Language :: Python :: 3.11
Classifier: Programming Language :: Python :: 3.12
Classifier: Topic :: Software Development :: Libraries :: Python Modules
Classifier: Topic :: Software Development :: Quality Assurance
Requires-Dist: psutil (>=6.0.0,<7.0.0)
Requires-Dist: pyjnius (==1.6.1)
Requires-Dist: pytest (>=8.3.2,<9.0.0)
Requires-Dist: pytest-forked (>=1.6.0,<2.0.0)
Requires-Dist: pytest-xdist (>=3.6.1,<4.0.0)
Project-URL: Bug Tracker, https://github.com/moraneus/pydejavu/issues
Project-URL: Documentation, https://github.com/moraneus/pydejavu/blob/main/README.md
Project-URL: Repository, https://github.com/moraneus/pydejavu
